murthy_lab_to_nwb/__init__.py
murthy_lab_to_nwb/cowley2022mapping/__init__.py
murthy_lab_to_nwb/cowley2022mapping/cowley2022mapping_courtship_convert_session.py
murthy_lab_to_nwb/cowley2022mapping/cowley2022mapping_imaging_convert_session.py
murthy_lab_to_nwb/cowley2022mapping/cowley2022mapping_nwbconverter.py
murthy_lab_to_nwb/cowley2022mapping/interfaces/__init__.py
murthy_lab_to_nwb/cowley2022mapping/interfaces/cowley2022mapping_courtship_audiointerface.py
murthy_lab_to_nwb/cowley2022mapping/interfaces/cowley2022mapping_courtship_audiosegmentationinterface.py
murthy_lab_to_nwb/cowley2022mapping/interfaces/cowley2022mapping_courtship_poseestimationinterface.py
murthy_lab_to_nwb/cowley2022mapping/interfaces/cowley2022mapping_courtship_stimuliinterface.py
murthy_lab_to_nwb/cowley2022mapping/interfaces/cowley2022mapping_imaging_behaviorinterface.py
murthy_lab_to_nwb/cowley2022mapping/interfaces/cowley2022mapping_imaging_imaginginterface.py
murthy_lab_to_nwb/cowley2022mapping/interfaces/cowley2022mapping_imaging_segmentationinterface.py
murthy_lab_to_nwb/cowley2022mapping/interfaces/cowley2022mapping_imaging_stimuliinterface.py
murthy_lab_to_nwb/cowley2022mapping/utils/__init__.py
murthy_lab_to_nwb/cowley2022mapping/utils/get_all_subjects_imaging.py
murthy_lab_to_nwb/cowley2022mapping/utils/imaging_visualization.py
murthy_lab_to_nwb/li2022ecephys/__init__.py
murthy_lab_to_nwb/li2022ecephys/li2022ecephys_convert_session.py
murthy_lab_to_nwb/li2022ecephys/li2022ecephysinterface.py
murthy_lab_to_nwb/li2022ecephys/li2022ecephysnwbconverter.py
murthy_lab_to_nwb-0.0.2.dist-info/LICENSE
murthy_lab_to_nwb-0.0.2.dist-info/METADATA
murthy_lab_to_nwb-0.0.2.dist-info/WHEEL
murthy_lab_to_nwb-0.0.2.dist-info/top_level.txt
murthy_lab_to_nwb-0.0.2.dist-info/RECORD
