Metadata-Version: 2.1
Name: murthy-lab-to-nwb
Version: 0.0.2
Summary: NWB conversion scripts, functions, and classes for the nwb conversion of Murthy lab
Home-page: https://github.com/catalystneuro/murthy-lab-to-nwb
Author: CatalystNeuro
Author-email: ben.dichter@catalystneuro.com
License: UNKNOWN
Platform: UNKNOWN
Requires-Python: >=3.7
Requires-Dist: neuroconv
Requires-Dist: nwbwidgets
Requires-Dist: nwbinspector
Requires-Dist: ndx-pose
Requires-Dist: ndx-events
Requires-Dist: ndx-sound
